.gitignore
LICENSE
README.md
setup.py
pipeline/tsimscripts_pipe.sh
resources/old_detector_defaults.txt
resources/filament_files/2zwh.json
resources/filament_files/2zwh.pdb
resources/test/input_1bxn.txt
tem_simulator_scripts.egg-info/PKG-INFO
tem_simulator_scripts.egg-info/SOURCES.txt
tem_simulator_scripts.egg-info/dependency_links.txt
tem_simulator_scripts.egg-info/entry_points.txt
tem_simulator_scripts.egg-info/requires.txt
tem_simulator_scripts.egg-info/top_level.txt
temsimscripts/__init__.py
temsimscripts/create_fiducials.ijm
temsimscripts/extract_noise.py
temsimscripts/extract_subvolumes.py
temsimscripts/generate_coordinates.py
temsimscripts/generate_filaments.py
temsimscripts/generate_input_file.py
temsimscripts/generate_map.py
temsimscripts/generate_raw_tilt.py
temsimscripts/generate_trans_file.py