Metadata-Version: 2.1
Name: tem-simulator-scripts
Version: 0.1.8.1
Summary: Support scripts for the TEM Simulator (V1.3)
Home-page: https://github.com/MPI-Dortmund/tem-simulator-scripts
Author: Thorsten Wagner, Markus Stabrin, Gavin Rice
Author-email: thorsten.wagner@mpi-dortmund.mpg.de
License: Mozilla Public License Version 2.0
Platform: UNKNOWN
Requires-Python: >=3.7.0, <3.10
License-File: LICENSE
